{
    "{'graph': 'spatial', 'input_width': '10', 'num_input_modules': '1', 'initial_block_type': 'basic', 'initial_residual': 'null', 'input_temporal_scales': '3', 'initial_main_width': '10', 'num_main_levels': '1', 'num_main_level_modules': '1', 'block_type': 'basic', 'bottleneck_factor': '4', 'residual': 'module', 'main_temporal_scales': '1', 'temporal_kernel_size': '7', 'se': 'inner', 'se_ratio': '4', 'se_type': 'relative', 'nonlinearity': 'relu', 'attention': 'channel', 'pool': 'spatial'}": {
        "best_auc_backup": 0.95425,
        "val_accuracy": 0.9411764705882353,
        "num_parameters": 258202,
        "num_flops": 1161292216,
        "best_loss": 0.6377865076065063,
        "best_auc": 0.9411764705882353,
        "training_validation_time_in_seconds": 10388.946252584457,
        "synflow_time_in_seconds": 23.145587682724,
        "synflow": 5792943785.076283,
        "snip_time_in_seconds": 20.779188871383667,
        "snip": 4427.77392578125,
        "grad_norm_time_in_seconds": 21.20145273208618,
        "grad_norm": 906.943359375,
        "fisher_time_in_seconds": 20.955618619918823,
        "fisher": 1718.0228271484375,
        "grasp_time_in_seconds": 23.71696949005127,
        "grasp": -53765.89453125,
        "flops_time_in_seconds": 21.640311002731323,
        "flops": 1153757936,
        "params_time_in_seconds": 22.607207775115967,
        "params": 258202
    },
    "{'graph': 'dis2', 'input_width': '12', 'num_input_modules': '3', 'initial_block_type': 'basic', 'initial_residual': 'module', 'input_temporal_scales': 'linear', 'initial_main_width': '6', 'num_main_levels': '2', 'num_main_level_modules': '3', 'block_type': 'basic', 'bottleneck_factor': '4', 'residual': 'dense', 'main_temporal_scales': '3', 'temporal_kernel_size': '9', 'se': 'null', 'se_ratio': '4', 'se_type': 'relative', 'nonlinearity': 'relu', 'attention': 'null', 'pool': 'spatial'}": {
        "best_auc_backup": 0.94771,
        "val_accuracy": 0.934640522875817,
        "num_parameters": 1028036,
        "num_flops": 4596044026,
        "best_loss": 0.6163479089736938,
        "best_auc": 0.934640522875817,
        "training_validation_time_in_seconds": 32973.27998280525,
        "synflow_time_in_seconds": 21.37535858154297,
        "synflow": 4.780555608718978e+34,
        "snip_time_in_seconds": 22.254226684570312,
        "snip": 30832.13671875,
        "grad_norm_time_in_seconds": 22.34468412399292,
        "grad_norm": 5439.349609375,
        "fisher_time_in_seconds": 22.615978002548218,
        "fisher": 25350.2734375,
        "grasp_time_in_seconds": 30.01943302154541,
        "grasp": -700697.0,
        "flops_time_in_seconds": 29.431946992874146,
        "flops": 4576759954,
        "params_time_in_seconds": 21.680131196975708,
        "params": 1028036
    },
    "{'graph': 'dis4+2', 'input_width': '12', 'num_input_modules': '3', 'initial_block_type': 'mbconv', 'initial_residual': 'module', 'input_temporal_scales': '1', 'initial_main_width': '10', 'num_main_levels': '1', 'num_main_level_modules': '1', 'block_type': 'basic', 'bottleneck_factor': '2', 'residual': 'block', 'main_temporal_scales': '3', 'temporal_kernel_size': '9', 'se': 'null', 'se_ratio': '2', 'se_type': 'relative', 'nonlinearity': 'relu', 'attention': 'channel', 'pool': 'spatial'}": {
        "best_auc_backup": 0.95207,
        "val_accuracy": 0.9651416122004357,
        "num_parameters": 133230,
        "num_flops": 478840750,
        "best_loss": 0.5758194923400879,
        "best_auc": 0.9651416122004357,
        "training_validation_time_in_seconds": 5042.634136199951,
        "synflow_time_in_seconds": 18.57494854927063,
        "synflow": 136141936952489.56,
        "snip_time_in_seconds": 16.089797735214233,
        "snip": 1629.7027587890625,
        "grad_norm_time_in_seconds": 16.81748056411743,
        "grad_norm": 820.4971313476562,
        "fisher_time_in_seconds": 16.254732131958008,
        "fisher": 274.2256164550781,
        "grasp_time_in_seconds": 18.12752938270569,
        "grasp": -38902.16015625,
        "flops_time_in_seconds": 26.86872696876526,
        "flops": 470401650,
        "params_time_in_seconds": 18.09111976623535,
        "params": 133230
    },
    "{'graph': 'dis2', 'input_width': '6', 'num_input_modules': '1', 'initial_block_type': 'basic', 'initial_residual': 'dense', 'input_temporal_scales': '3', 'initial_main_width': '10', 'num_main_levels': '2', 'num_main_level_modules': '2', 'block_type': 'basic', 'bottleneck_factor': '2', 'residual': 'dense', 'main_temporal_scales': 'linear', 'temporal_kernel_size': '9', 'se': 'outer', 'se_ratio': '4', 'se_type': 'absolute', 'nonlinearity': 'relu', 'attention': 'channel', 'pool': 'spatial'}": {
        "best_auc_backup": 0.96296,
        "synflow_time_in_seconds": 21.002994537353516,
        "synflow": 1.667680936470469e+18,
        "snip_time_in_seconds": 20.87068247795105,
        "snip": 8033.08251953125,
        "grad_norm_time_in_seconds": 19.95136785507202,
        "grad_norm": 1757.3746337890625,
        "fisher_time_in_seconds": 20.924375534057617,
        "fisher": 6101.2001953125,
        "grasp_time_in_seconds": 22.954227924346924,
        "grasp": -144111.1875,
        "val_accuracy": 0.9324618736383443,
        "num_parameters": 190281,
        "num_flops": 336703664,
        "best_loss": 0.5651578903198242,
        "best_auc": 0.9324618736383443,
        "training_validation_time_in_seconds": 6670.462215185165,
        "flops_time_in_seconds": 18.56035304069519,
        "flops": 331871026,
        "params_time_in_seconds": 22.839662075042725,
        "params": 190281
    },
    "{'graph': 'dis4', 'input_width': '6', 'num_input_modules': '1', 'initial_block_type': 'bottleneck', 'initial_residual': 'module', 'input_temporal_scales': '2', 'initial_main_width': '10', 'num_main_levels': '2', 'num_main_level_modules': '1', 'block_type': 'basic', 'bottleneck_factor': '2', 'residual': 'module', 'main_temporal_scales': 'linear', 'temporal_kernel_size': '7', 'se': 'null', 'se_ratio': '2', 'se_type': 'absolute', 'nonlinearity': 'relu', 'attention': 'channel', 'pool': 'global'}": {
        "best_auc_backup": 0.94118,
        "synflow_time_in_seconds": 13.901320219039917,
        "synflow": 1957629243055.7974,
        "snip_time_in_seconds": 14.007157564163208,
        "snip": 110.72624206542969,
        "grad_norm_time_in_seconds": 13.92068600654602,
        "grad_norm": 43.38821792602539,
        "fisher_time_in_seconds": 14.280126094818115,
        "fisher": 2.8901219367980957,
        "grasp_time_in_seconds": 15.528184652328491,
        "grasp": -13.017105102539062,
        "val_accuracy": 0.9302832244008714,
        "num_parameters": 71700,
        "num_flops": 145577774,
        "best_loss": 0.5667494535446167,
        "best_auc": 0.9302832244008714,
        "training_validation_time_in_seconds": 4039.4309227466583,
        "flops_time_in_seconds": 17.061206340789795,
        "flops": 141482926,
        "params_time_in_seconds": 17.95828151702881,
        "params": 71700
    },
    "{'graph': 'spatial', 'input_width': '12', 'num_input_modules': '2', 'initial_block_type': 'mbconv', 'initial_residual': 'dense', 'input_temporal_scales': '3', 'initial_main_width': '10', 'num_main_levels': '1', 'num_main_level_modules': '2', 'block_type': 'mbconv', 'bottleneck_factor': '4', 'residual': 'block', 'main_temporal_scales': '2', 'temporal_kernel_size': '9', 'se': 'null', 'se_ratio': '2', 'se_type': 'relative', 'nonlinearity': 'swish', 'attention': 'null', 'pool': 'spatial'}": {
        "best_auc_backup": 0.96078,
        "synflow_time_in_seconds": 20.159706354141235,
        "synflow": 111367074417560.38,
        "snip_time_in_seconds": 21.671406030654907,
        "snip": 306.2809753417969,
        "grad_norm_time_in_seconds": 21.10827612876892,
        "grad_norm": 261.18878173828125,
        "fisher_time_in_seconds": 20.989484071731567,
        "fisher": 11.744089126586914,
        "grasp_time_in_seconds": 27.95884943008423,
        "grasp": -1079.421630859375,
        "val_accuracy": 0.9498910675381264,
        "num_parameters": 75064,
        "num_flops": 400431912,
        "best_loss": 0.5367807149887085,
        "best_auc": 0.9498910675381264,
        "training_validation_time_in_seconds": 7011.199683904648,
        "flops_time_in_seconds": 31.369147062301636,
        "flops": 375149712,
        "params_time_in_seconds": 20.72666645050049,
        "params": 75064
    },
    "{'graph': 'spatial', 'input_width': '8', 'num_input_modules': '2', 'initial_block_type': 'basic', 'initial_residual': 'block', 'input_temporal_scales': '1', 'initial_main_width': '8', 'num_main_levels': '1', 'num_main_level_modules': '1', 'block_type': 'basic', 'bottleneck_factor': '4', 'residual': 'module', 'main_temporal_scales': '3', 'temporal_kernel_size': '9', 'se': 'inner', 'se_ratio': '4', 'se_type': 'relative', 'nonlinearity': 'swish', 'attention': 'channel', 'pool': 'spatial'}": {
        "best_auc_backup": 0.96078,
        "synflow_time_in_seconds": 13.977802038192749,
        "synflow": 489204136052.8926,
        "snip_time_in_seconds": 14.047701597213745,
        "snip": 1954.3118896484375,
        "grad_norm_time_in_seconds": 14.084190845489502,
        "grad_norm": 479.507568359375,
        "fisher_time_in_seconds": 14.222025156021118,
        "fisher": 448.7947998046875,
        "grasp_time_in_seconds": 16.451083660125732,
        "grasp": -10859.6875,
        "val_accuracy": 0.9455337690631808,
        "num_parameters": 205827,
        "num_flops": 778286600,
        "best_loss": 0.6101921796798706,
        "best_auc": 0.9455337690631808,
        "training_validation_time_in_seconds": 5059.042128324509,
        "flops_time_in_seconds": 17.30520462989807,
        "flops": 770995888,
        "params_time_in_seconds": 17.314311027526855,
        "params": 205827
    },
    "{'graph': 'dis2', 'input_width': '10', 'num_input_modules': '2', 'initial_block_type': 'mbconv', 'initial_residual': 'null', 'input_temporal_scales': '2', 'initial_main_width': '6', 'num_main_levels': '1', 'num_main_level_modules': '1', 'block_type': 'mbconv', 'bottleneck_factor': '4', 'residual': 'block', 'main_temporal_scales': '3', 'temporal_kernel_size': '7', 'se': 'inner', 'se_ratio': '2', 'se_type': 'absolute', 'nonlinearity': 'relu', 'attention': 'channel', 'pool': 'spatial'}": {
        "best_auc_backup": 0.96514,
        "synflow_time_in_seconds": 14.971477746963501,
        "synflow": 1045312791534.7395,
        "snip_time_in_seconds": 14.537980556488037,
        "snip": 1072.3983154296875,
        "grad_norm_time_in_seconds": 15.059612035751343,
        "grad_norm": 863.8291015625,
        "fisher_time_in_seconds": 14.625702142715454,
        "fisher": 187.0600128173828,
        "grasp_time_in_seconds": 18.67865800857544,
        "grasp": -36810.0234375,
        "val_accuracy": 0.9237472766884531,
        "num_parameters": 64585,
        "num_flops": 186061460,
        "best_loss": 0.5860823392868042,
        "best_auc": 0.9237472766884531,
        "training_validation_time_in_seconds": 3999.8333814144135,
        "flops_time_in_seconds": 23.038514852523804,
        "flops": 170714634,
        "params_time_in_seconds": 18.039539337158203,
        "params": 64585
    },
    "{'graph': 'dis4', 'input_width': '12', 'num_input_modules': '2', 'initial_block_type': 'bottleneck', 'initial_residual': 'block', 'input_temporal_scales': '3', 'initial_main_width': '12', 'num_main_levels': '2', 'num_main_level_modules': '1', 'block_type': 'mbconv', 'bottleneck_factor': '4', 'residual': 'dense', 'main_temporal_scales': '1', 'temporal_kernel_size': '5', 'se': 'inner', 'se_ratio': '4', 'se_type': 'absolute', 'nonlinearity': 'relu', 'attention': 'null', 'pool': 'spatial'}": {
        "best_auc_backup": 0.93028,
        "synflow_time_in_seconds": 21.678950786590576,
        "synflow": 2.827948344336725e+18,
        "snip_time_in_seconds": 21.475317239761353,
        "snip": 2376.353515625,
        "grad_norm_time_in_seconds": 21.58001136779785,
        "grad_norm": 886.7848510742188,
        "fisher_time_in_seconds": 21.56502628326416,
        "fisher": 303.1318664550781,
        "grasp_time_in_seconds": 30.23477292060852,
        "grasp": -15906.8388671875,
        "val_accuracy": 0.9455337690631809,
        "num_parameters": 251518,
        "num_flops": 932597004,
        "best_loss": 0.5692457556724548,
        "best_auc": 0.9455337690631809,
        "training_validation_time_in_seconds": 11229.48780798912,
        "flops_time_in_seconds": 20.430335998535156,
        "flops": 899549532,
        "params_time_in_seconds": 18.230137825012207,
        "params": 251518
    },
    "{'graph': 'spatial', 'input_width': '6', 'num_input_modules': '2', 'initial_block_type': 'mbconv', 'initial_residual': 'module', 'input_temporal_scales': '1', 'initial_main_width': '6', 'num_main_levels': '1', 'num_main_level_modules': '1', 'block_type': 'basic', 'bottleneck_factor': '2', 'residual': 'dense', 'main_temporal_scales': '1', 'temporal_kernel_size': '7', 'se': 'outer', 'se_ratio': '4', 'se_type': 'relative', 'nonlinearity': 'relu', 'attention': 'joint', 'pool': 'spatial'}": {
        "best_auc_backup": 0.91721,
        "synflow_time_in_seconds": 20.715540170669556,
        "synflow": 838790062.0718867,
        "snip_time_in_seconds": 20.28411626815796,
        "snip": 604.0650634765625,
        "grad_norm_time_in_seconds": 20.92750906944275,
        "grad_norm": 463.7812194824219,
        "fisher_time_in_seconds": 20.61818766593933,
        "fisher": 115.31053924560547,
        "grasp_time_in_seconds": 21.30072522163391,
        "grasp": -12875.6748046875,
        "val_accuracy": 0.9324618736383441,
        "num_parameters": 40980,
        "num_flops": 63044826,
        "best_loss": 0.5306299924850464,
        "best_auc": 0.9324618736383441,
        "training_validation_time_in_seconds": 2379.817038536072,
        "flops_time_in_seconds": 19.660767078399658,
        "flops": 59129630,
        "params_time_in_seconds": 19.65550136566162,
        "params": 40980
    },
    "{'graph': 'dis4', 'input_width': 8, 'num_input_modules': 3, 'initial_block_type': 'mbconv', 'initial_residual': 'dense', 'input_temporal_scales': 2, 'initial_main_width': 10, 'num_main_levels': 2, 'num_main_level_modules': 1, 'block_type': 'basic', 'bottleneck_factor': 4, 'residual': 'null', 'main_temporal_scales': 2, 'temporal_kernel_size': 3, 'se': 'outer', 'se_ratio': 2, 'se_type': 'relative', 'nonlinearity': 'swish', 'attention': 'channel', 'pool': 'global'}": {
        "best_auc_backup": 0.9433551198257081,
        "synflow_time_in_seconds": 20.77052354812622,
        "synflow": 6.427480455959004e+17,
        "snip_time_in_seconds": 21.561298847198486,
        "snip": 307.4640197753906,
        "grad_norm_time_in_seconds": 21.388190507888794,
        "grad_norm": 98.5051040649414,
        "fisher_time_in_seconds": 21.16530752182007,
        "fisher": 3.9476332664489746,
        "grasp_time_in_seconds": 26.7545428276062,
        "grasp": 93.4649658203125,
        "val_accuracy": 0.9433551198257081,
        "num_parameters": 304502,
        "num_flops": 946660998,
        "best_loss": 0.5672889947891235,
        "best_auc": 0.9433551198257081,
        "training_validation_time_in_seconds": 12833.250183105469,
        "flops_time_in_seconds": 23.944584369659424,
        "flops": 930382550,
        "params_time_in_seconds": 23.721182823181152,
        "params": 304502
    },
    "{'graph': 'spatial', 'input_width': 8, 'num_input_modules': 2, 'initial_block_type': 'bottleneck', 'initial_residual': 'null', 'input_temporal_scales': 2, 'initial_main_width': 8, 'num_main_levels': 1, 'num_main_level_modules': 1, 'block_type': 'bottleneck', 'bottleneck_factor': 2, 'residual': 'module', 'main_temporal_scales': 1, 'temporal_kernel_size': 3, 'se': 'null', 'se_ratio': 4, 'se_type': 'relative', 'nonlinearity': 'relu', 'attention': 'channel', 'pool': 'spatial'}": {
        "best_auc_backup": 0.9150326797385621,
        "synflow_time_in_seconds": 14.52631163597107,
        "synflow": 8050109874898442.0,
        "snip_time_in_seconds": 14.39479374885559,
        "snip": 1640.135009765625,
        "grad_norm_time_in_seconds": 14.316936492919922,
        "grad_norm": 604.861083984375,
        "fisher_time_in_seconds": 14.695000886917114,
        "fisher": 369.3015441894531,
        "grasp_time_in_seconds": 17.818241357803345,
        "grasp": -12308.322265625,
        "val_accuracy": 0.9150326797385621,
        "num_parameters": 42239,
        "num_flops": 116564304,
        "best_loss": 0.5545167922973633,
        "best_auc": 0.9150326797385621,
        "training_validation_time_in_seconds": 4133.038311958313,
        "flops_time_in_seconds": 29.46962547302246,
        "flops": 109099648,
        "params_time_in_seconds": 20.057787895202637,
        "params": 42239
    },
    "{'graph': 'dis4', 'input_width': 8, 'num_input_modules': 2, 'initial_block_type': 'basic', 'initial_residual': 'null', 'input_temporal_scales': 'linear', 'initial_main_width': 8, 'num_main_levels': 2, 'num_main_level_modules': 1, 'block_type': 'mbconv', 'bottleneck_factor': 4, 'residual': 'block', 'main_temporal_scales': 1, 'temporal_kernel_size': 5, 'se': 'inner', 'se_ratio': 2, 'se_type': 'relative', 'nonlinearity': 'relu', 'attention': 'frame', 'pool': 'global'}": {
        "best_auc_backup": 0.9498910675381264,
        "synflow_time_in_seconds": 14.385239124298096,
        "synflow": 1.5977318196222166e+77,
        "snip_time_in_seconds": 14.868478059768677,
        "snip": 83.30180358886719,
        "grad_norm_time_in_seconds": 14.71427297592163,
        "grad_norm": 47.07285690307617,
        "fisher_time_in_seconds": 14.938329458236694,
        "fisher": 0.7918214797973633,
        "grasp_time_in_seconds": 18.91830062866211,
        "grasp": -26.751190185546875,
        "val_accuracy": 0.9498910675381264,
        "num_parameters": 156814,
        "num_flops": 381278664,
        "best_loss": 0.7583585977554321,
        "best_auc": 0.9498910675381264,
        "training_validation_time_in_seconds": 5565.453315496445,
        "flops_time_in_seconds": 23.061280488967896,
        "flops": 365284816,
        "params_time_in_seconds": 20.22869300842285,
        "params": 156814
    },
    "{'graph': 'dis4+2', 'input_width': 10, 'num_input_modules': 1, 'initial_block_type': 'basic', 'initial_residual': 'dense', 'input_temporal_scales': 2, 'initial_main_width': 10, 'num_main_levels': 1, 'num_main_level_modules': 3, 'block_type': 'bottleneck', 'bottleneck_factor': 2, 'residual': 'null', 'main_temporal_scales': 'linear', 'temporal_kernel_size': 3, 'se': 'outer', 'se_ratio': 4, 'se_type': 'absolute', 'nonlinearity': 'swish', 'attention': 'joint', 'pool': 'global'}": {
        "best_auc_backup": 0.9019607843137254,
        "synflow_time_in_seconds": 14.47197961807251,
        "synflow": 2.870672038233072e+17,
        "snip_time_in_seconds": 14.83859133720398,
        "snip": 20.620908737182617,
        "grad_norm_time_in_seconds": 14.643961191177368,
        "grad_norm": 11.03632640838623,
        "fisher_time_in_seconds": 14.082824468612671,
        "fisher": 0.13288754224777222,
        "grasp_time_in_seconds": 15.403849601745605,
        "grasp": 2.1345651149749756,
        "val_accuracy": 0.9019607843137254,
        "num_parameters": 48336,
        "num_flops": 130492278,
        "best_loss": 0.5737629532814026,
        "best_auc": 0.9019607843137254,
        "training_validation_time_in_seconds": 3581.109978914261,
        "flops_time_in_seconds": 22.909850120544434,
        "flops": 125089410,
        "params_time_in_seconds": 19.731950283050537,
        "params": 48336
    },
    "{'graph': 'dis4+2', 'input_width': 10, 'num_input_modules': 1, 'initial_block_type': 'mbconv', 'initial_residual': 'null', 'input_temporal_scales': 1, 'initial_main_width': 8, 'num_main_levels': 1, 'num_main_level_modules': 3, 'block_type': 'bottleneck', 'bottleneck_factor': 2, 'residual': 'dense', 'main_temporal_scales': 1, 'temporal_kernel_size': 9, 'se': 'both', 'se_ratio': 2, 'se_type': 'relative', 'nonlinearity': 'swish', 'attention': 'frame', 'pool': 'spatial'}": {
        "best_auc_backup": 0.710239651416122,
        "synflow_time_in_seconds": 20.921164512634277,
        "synflow": 1.803196796356179e+83,
        "snip_time_in_seconds": 21.075016736984253,
        "snip": 1547.8543701171875,
        "grad_norm_time_in_seconds": 20.707074880599976,
        "grad_norm": 1247.0706787109375,
        "fisher_time_in_seconds": 20.871283769607544,
        "fisher": 1074.28515625,
        "grasp_time_in_seconds": 21.993657112121582,
        "grasp": -446552.6875,
        "val_accuracy": 0.710239651416122,
        "num_parameters": 37272,
        "num_flops": 54178472,
        "best_loss": 0.6796025037765503,
        "best_auc": 0.710239651416122,
        "training_validation_time_in_seconds": 296.82968735694885,
        "flops_time_in_seconds": 20.165926456451416,
        "flops": 50176472,
        "params_time_in_seconds": 17.031885623931885,
        "params": 37272
    },
    "{'graph': 'dis2', 'input_width': 10, 'num_input_modules': 3, 'initial_block_type': 'mbconv', 'initial_residual': 'block', 'input_temporal_scales': 'linear', 'initial_main_width': 8, 'num_main_levels': 2, 'num_main_level_modules': 1, 'block_type': 'bottleneck', 'bottleneck_factor': 4, 'residual': 'null', 'main_temporal_scales': 2, 'temporal_kernel_size': 5, 'se': 'outer', 'se_ratio': 2, 'se_type': 'absolute', 'nonlinearity': 'swish', 'attention': 'channel', 'pool': 'spatial'}": {
        "best_auc_backup": 0.9586056644880174,
        "synflow_time_in_seconds": 21.879956245422363,
        "synflow": 1.8654451676985132e+28,
        "snip_time_in_seconds": 22.10108208656311,
        "snip": 3735.025634765625,
        "grad_norm_time_in_seconds": 21.56009578704834,
        "grad_norm": 1881.380615234375,
        "fisher_time_in_seconds": 22.055745363235474,
        "fisher": 721.6151733398438,
        "grasp_time_in_seconds": 28.81505012512207,
        "grasp": -261030.671875,
        "val_accuracy": 0.9586056644880174,
        "num_parameters": 246736,
        "num_flops": 599345158,
        "best_loss": 0.5442670583724976,
        "best_auc": 0.9586056644880174,
        "training_validation_time_in_seconds": 11228.14102602005,
        "flops_time_in_seconds": 23.5278377532959,
        "flops": 577743226,
        "params_time_in_seconds": 18.74813461303711,
        "params": 246736
    },
    "{'graph': 'dis2', 'input_width': 10, 'num_input_modules': 3, 'initial_block_type': 'mbconv', 'initial_residual': 'block', 'input_temporal_scales': 1, 'initial_main_width': 8, 'num_main_levels': 2, 'num_main_level_modules': 1, 'block_type': 'basic', 'bottleneck_factor': 2, 'residual': 'block', 'main_temporal_scales': 2, 'temporal_kernel_size': 5, 'se': 'null', 'se_ratio': 4, 'se_type': 'absolute', 'nonlinearity': 'relu', 'attention': 'channel', 'pool': 'global'}": {
        "best_auc_backup": 0.9498910675381264,
        "synflow_time_in_seconds": 16.82688307762146,
        "synflow": 98388646758419.44,
        "snip_time_in_seconds": 14.224120378494263,
        "snip": 117.50580596923828,
        "grad_norm_time_in_seconds": 14.472506999969482,
        "grad_norm": 50.015167236328125,
        "fisher_time_in_seconds": 14.532195091247559,
        "fisher": 1.7678112983703613,
        "grasp_time_in_seconds": 16.41859269142151,
        "grasp": -1.2184295654296875,
        "val_accuracy": 0.9498910675381264,
        "num_parameters": 84274,
        "num_flops": 231347588,
        "best_loss": 0.5002882480621338,
        "best_auc": 0.9498910675381264,
        "training_validation_time_in_seconds": 4213.829631567001,
        "flops_time_in_seconds": 17.505779504776,
        "flops": 223669452,
        "params_time_in_seconds": 24.005651473999023,
        "params": 84274
    },
    "{'graph': 'dis4+2', 'input_width': 6, 'num_input_modules': 2, 'initial_block_type': 'bottleneck', 'initial_residual': 'block', 'input_temporal_scales': 1, 'initial_main_width': 12, 'num_main_levels': 2, 'num_main_level_modules': 1, 'block_type': 'basic', 'bottleneck_factor': 2, 'residual': 'module', 'main_temporal_scales': 2, 'temporal_kernel_size': 3, 'se': 'null', 'se_ratio': 2, 'se_type': 'absolute', 'nonlinearity': 'swish', 'attention': 'joint', 'pool': 'global'}": {
        "best_auc_backup": 0.9629629629629629,
        "synflow_time_in_seconds": 19.36203169822693,
        "synflow": 20987777118545.086,
        "snip_time_in_seconds": 20.17423176765442,
        "snip": 110.65496063232422,
        "grad_norm_time_in_seconds": 20.175829648971558,
        "grad_norm": 43.653446197509766,
        "fisher_time_in_seconds": 20.543683767318726,
        "fisher": 1.3171066045761108,
        "grasp_time_in_seconds": 21.496491193771362,
        "grasp": -31.427764892578125,
        "val_accuracy": 0.9629629629629629,
        "num_parameters": 87776,
        "num_flops": 141504710,
        "best_loss": 0.5050603747367859,
        "best_auc": 0.9629629629629629,
        "training_validation_time_in_seconds": 4665.439769029617,
        "flops_time_in_seconds": 18.864641904830933,
        "flops": 136956126,
        "params_time_in_seconds": 18.425522089004517,
        "params": 87776
    },
    "{'graph': 'dis4', 'input_width': 6, 'num_input_modules': 2, 'initial_block_type': 'mbconv', 'initial_residual': 'dense', 'input_temporal_scales': 2, 'initial_main_width': 8, 'num_main_levels': 2, 'num_main_level_modules': 3, 'block_type': 'bottleneck', 'bottleneck_factor': 4, 'residual': 'block', 'main_temporal_scales': 2, 'temporal_kernel_size': 5, 'se': 'both', 'se_ratio': 2, 'se_type': 'absolute', 'nonlinearity': 'relu', 'attention': 'channel', 'pool': 'spatial'}": {
        "best_auc_backup": 0.9455337690631809,
        "synflow_time_in_seconds": 17.957124710083008,
        "synflow": 1.742692776244318e+44,
        "snip_time_in_seconds": 15.624341249465942,
        "snip": 17444.2421875,
        "grad_norm_time_in_seconds": 15.732989072799683,
        "grad_norm": 5846.74169921875,
        "fisher_time_in_seconds": 15.95767855644226,
        "fisher": 9610.298828125,
        "grasp_time_in_seconds": 20.180858850479126,
        "grasp": -809633.375,
        "val_accuracy": 0.9455337690631809,
        "num_parameters": 337131,
        "num_flops": 353765174,
        "best_loss": 0.5361509323120117,
        "best_auc": 0.9455337690631809,
        "training_validation_time_in_seconds": 8896.907232999802,
        "flops_time_in_seconds": 23.006317615509033,
        "flops": 337931452,
        "params_time_in_seconds": 26.590160131454468,
        "params": 337131
    },
    "{'graph': 'dis4+2', 'input_width': 12, 'num_input_modules': 1, 'initial_block_type': 'bottleneck', 'initial_residual': 'block', 'input_temporal_scales': 1, 'initial_main_width': 8, 'num_main_levels': 2, 'num_main_level_modules': 2, 'block_type': 'mbconv', 'bottleneck_factor': 2, 'residual': 'module', 'main_temporal_scales': 1, 'temporal_kernel_size': 5, 'se': 'null', 'se_ratio': 2, 'se_type': 'absolute', 'nonlinearity': 'relu', 'attention': 'null', 'pool': 'global'}": {
        "synflow_time_in_seconds": 16.979174613952637,
        "synflow": 170137536427862.9,
        "snip_time_in_seconds": 14.680490255355835,
        "snip": 84.14675903320312,
        "grad_norm_time_in_seconds": 14.61926555633545,
        "grad_norm": 48.1862907409668,
        "fisher_time_in_seconds": 14.593848943710327,
        "fisher": 1.4606703519821167,
        "grasp_time_in_seconds": 15.562835454940796,
        "grasp": -124.82859802246094,
        "val_accuracy": 0.7167755991285403,
        "num_parameters": 35974,
        "num_flops": 86677534,
        "best_loss": 0.673295259475708,
        "best_auc": 0.7167755991285403,
        "training_validation_time_in_seconds": 263.4512267112732,
        "flops_time_in_seconds": 15.846871614456177,
        "flops": 81607638,
        "params_time_in_seconds": 20.133298635482788,
        "params": 35974
    },
    "{'graph': 'dis2', 'input_width': 8, 'num_input_modules': 3, 'initial_block_type': 'mbconv', 'initial_residual': 'module', 'input_temporal_scales': 1, 'initial_main_width': 10, 'num_main_levels': 1, 'num_main_level_modules': 2, 'block_type': 'bottleneck', 'bottleneck_factor': 4, 'residual': 'null', 'main_temporal_scales': 'linear', 'temporal_kernel_size': 5, 'se': 'inner', 'se_ratio': 2, 'se_type': 'relative', 'nonlinearity': 'relu', 'attention': 'frame', 'pool': 'global'}": {
        "best_auc_backup": 0.6840958605664487,
        "synflow_time_in_seconds": 20.977203607559204,
        "synflow": 2.981321546666302e+182,
        "snip_time_in_seconds": 20.96644377708435,
        "snip": 139.893310546875,
        "grad_norm_time_in_seconds": 20.901591300964355,
        "grad_norm": 133.6033477783203,
        "fisher_time_in_seconds": 20.953219890594482,
        "fisher": 2.0433459281921387,
        "grasp_time_in_seconds": 24.482248783111572,
        "grasp": 15512.2421875,
        "val_accuracy": 0.6840958605664487,
        "num_parameters": 75169,
        "num_flops": 172644660,
        "best_loss": 0.6968922019004822,
        "best_auc": 0.6840958605664487,
        "training_validation_time_in_seconds": 564.1261804103851,
        "flops_time_in_seconds": 19.982306480407715,
        "flops": 160734360,
        "params_time_in_seconds": 18.106560707092285,
        "params": 75169
    },
    "{'graph': 'dis2', 'input_width': 6, 'num_input_modules': 3, 'initial_block_type': 'mbconv', 'initial_residual': 'module', 'input_temporal_scales': 1, 'initial_main_width': 6, 'num_main_levels': 1, 'num_main_level_modules': 3, 'block_type': 'basic', 'bottleneck_factor': 2, 'residual': 'dense', 'main_temporal_scales': 1, 'temporal_kernel_size': 7, 'se': 'both', 'se_ratio': 2, 'se_type': 'relative', 'nonlinearity': 'relu', 'attention': 'channel', 'pool': 'global'}": {
        "best_auc_backup": 0.9411764705882353,
        "synflow_time_in_seconds": 20.64514684677124,
        "synflow": 5597519241219.058,
        "snip_time_in_seconds": 20.621142625808716,
        "snip": 238.26976013183594,
        "grad_norm_time_in_seconds": 20.649109601974487,
        "grad_norm": 194.90325927734375,
        "fisher_time_in_seconds": 20.712815284729004,
        "fisher": 15.116687774658203,
        "grasp_time_in_seconds": 22.57154369354248,
        "grasp": 348.3062744140625,
        "val_accuracy": 0.9411764705882353,
        "num_parameters": 49682,
        "num_flops": 108605450,
        "best_loss": 0.573283314704895,
        "best_auc": 0.9411764705882353,
        "training_validation_time_in_seconds": 3130.448093652725,
        "flops_time_in_seconds": 19.37494945526123,
        "flops": 103437590,
        "params_time_in_seconds": 19.54564118385315,
        "params": 49682
    },
    "{'graph': 'dis4', 'input_width': 10, 'num_input_modules': 1, 'initial_block_type': 'mbconv', 'initial_residual': 'module', 'input_temporal_scales': 2, 'initial_main_width': 10, 'num_main_levels': 2, 'num_main_level_modules': 1, 'block_type': 'basic', 'bottleneck_factor': 4, 'residual': 'dense', 'main_temporal_scales': 1, 'temporal_kernel_size': 3, 'se': 'inner', 'se_ratio': 4, 'se_type': 'relative', 'nonlinearity': 'relu', 'attention': 'joint', 'pool': 'global'}": {
        "best_auc_backup": 0.9607843137254902,
        "synflow_time_in_seconds": 14.798785924911499,
        "synflow": 8253981167.321292,
        "snip_time_in_seconds": 15.548662185668945,
        "snip": 185.6868438720703,
        "grad_norm_time_in_seconds": 15.481537342071533,
        "grad_norm": 77.15164184570312,
        "fisher_time_in_seconds": 14.811586380004883,
        "fisher": 3.5316362380981445,
        "grasp_time_in_seconds": 17.94661569595337,
        "grasp": -5.2886505126953125,
        "val_accuracy": 0.9607843137254902,
        "num_parameters": 141841,
        "num_flops": 306354056,
        "best_loss": 0.4826425015926361,
        "best_auc": 0.9607843137254902,
        "training_validation_time_in_seconds": 4513.620879888535,
        "flops_time_in_seconds": 18.278154850006104,
        "flops": 297140036,
        "params_time_in_seconds": 16.79782724380493,
        "params": 141841
    },
    "{'graph': 'dis4', 'input_width': 10, 'num_input_modules': 2, 'initial_block_type': 'mbconv', 'initial_residual': 'block', 'input_temporal_scales': 'linear', 'initial_main_width': 12, 'num_main_levels': 2, 'num_main_level_modules': 2, 'block_type': 'bottleneck', 'bottleneck_factor': 4, 'residual': 'dense', 'main_temporal_scales': 'linear', 'temporal_kernel_size': 3, 'se': 'inner', 'se_ratio': 2, 'se_type': 'relative', 'nonlinearity': 'relu', 'attention': 'channel', 'pool': 'spatial'}": {
        "best_auc_backup": 0.8910675381263617,
        "synflow_time_in_seconds": 28.043496131896973,
        "synflow": 1.8925903852634427e+35,
        "snip_time_in_seconds": 28.453705549240112,
        "snip": 25825.68359375,
        "grad_norm_time_in_seconds": 28.959601402282715,
        "grad_norm": 7918.6396484375,
        "fisher_time_in_seconds": 28.721547842025757,
        "fisher": 35160.82421875,
        "grasp_time_in_seconds": 39.57428503036499,
        "grasp": -1066354.25,
        "val_accuracy": 0.8910675381263617,
        "num_parameters": 523770,
        "num_flops": 591084848,
        "best_loss": 0.6143261194229126,
        "best_auc": 0.8910675381263617,
        "training_validation_time_in_seconds": 8086.316123485565,
        "flops_time_in_seconds": 20.494245290756226,
        "flops": 571525640,
        "params_time_in_seconds": 20.15302848815918,
        "params": 523770
    },
    "{'graph': 'dis4', 'input_width': 12, 'num_input_modules': 2, 'initial_block_type': 'bottleneck', 'initial_residual': 'dense', 'input_temporal_scales': 3, 'initial_main_width': 8, 'num_main_levels': 2, 'num_main_level_modules': 1, 'block_type': 'bottleneck', 'bottleneck_factor': 2, 'residual': 'dense', 'main_temporal_scales': 2, 'temporal_kernel_size': 9, 'se': 'both', 'se_ratio': 4, 'se_type': 'relative', 'nonlinearity': 'swish', 'attention': 'null', 'pool': 'spatial'}": {
        "best_auc_backup": 0.886710239651416,
        "synflow_time_in_seconds": 22.996798992156982,
        "synflow": 5.194093307049498e+26,
        "snip_time_in_seconds": 24.148862838745117,
        "snip": 1842.415771484375,
        "grad_norm_time_in_seconds": 23.10753583908081,
        "grad_norm": 625.1565551757812,
        "fisher_time_in_seconds": 23.774949312210083,
        "fisher": 245.84414672851562,
        "grasp_time_in_seconds": 28.70805335044861,
        "grasp": -13337.7236328125,
        "val_accuracy": 0.886710239651416,
        "num_parameters": 140646,
        "num_flops": 531420820,
        "best_loss": 0.5788823366165161,
        "best_auc": 0.886710239651416,
        "training_validation_time_in_seconds": 8701.74148273468,
        "flops_time_in_seconds": 23.96940016746521,
        "flops": 516886252,
        "params_time_in_seconds": 19.602184534072876,
        "params": 140646
    },
    "{'graph': 'dis4+2', 'input_width': 6, 'num_input_modules': 1, 'initial_block_type': 'basic', 'initial_residual': 'module', 'input_temporal_scales': 2, 'initial_main_width': 6, 'num_main_levels': 1, 'num_main_level_modules': 2, 'block_type': 'basic', 'bottleneck_factor': 2, 'residual': 'block', 'main_temporal_scales': 1, 'temporal_kernel_size': 9, 'se': 'both', 'se_ratio': 2, 'se_type': 'absolute', 'nonlinearity': 'relu', 'attention': 'joint', 'pool': 'spatial'}": {
        "best_auc_backup": 0.9607843137254901,
        "synflow_time_in_seconds": 15.247474431991577,
        "synflow": 46705956463.47589,
        "snip_time_in_seconds": 14.670011520385742,
        "snip": 669.4261474609375,
        "grad_norm_time_in_seconds": 14.399204969406128,
        "grad_norm": 293.1961975097656,
        "fisher_time_in_seconds": 14.43252944946289,
        "fisher": 116.97157287597656,
        "grasp_time_in_seconds": 15.503135681152344,
        "grasp": -3813.428466796875,
        "val_accuracy": 0.9607843137254901,
        "num_parameters": 43457,
        "num_flops": 102139994,
        "best_loss": 0.5545949935913086,
        "best_auc": 0.9607843137254901,
        "training_validation_time_in_seconds": 3454.2254269123077,
        "flops_time_in_seconds": 21.0272159576416,
        "flops": 99686454,
        "params_time_in_seconds": 19.027774810791016,
        "params": 43457
    },
    "{'graph': 'spatial', 'input_width': 6, 'num_input_modules': 1, 'initial_block_type': 'bottleneck', 'initial_residual': 'null', 'input_temporal_scales': 'linear', 'initial_main_width': 6, 'num_main_levels': 1, 'num_main_level_modules': 1, 'block_type': 'mbconv', 'bottleneck_factor': 4, 'residual': 'module', 'main_temporal_scales': 1, 'temporal_kernel_size': 9, 'se': 'inner', 'se_ratio': 4, 'se_type': 'absolute', 'nonlinearity': 'relu', 'attention': 'channel', 'pool': 'global'}": {
        "best_auc_backup": 0.9520697167755992,
        "synflow_time_in_seconds": 15.909928321838379,
        "synflow": 14678358.536689034,
        "snip_time_in_seconds": 14.027956247329712,
        "snip": 19.765708923339844,
        "grad_norm_time_in_seconds": 14.023411273956299,
        "grad_norm": 12.1727294921875,
        "fisher_time_in_seconds": 14.008033990859985,
        "fisher": 0.26721617579460144,
        "grasp_time_in_seconds": 15.142404556274414,
        "grasp": 1.2319674491882324,
        "val_accuracy": 0.9520697167755992,
        "num_parameters": 20891,
        "num_flops": 38436280,
        "best_loss": 0.5800998210906982,
        "best_auc": 0.9520697167755992,
        "training_validation_time_in_seconds": 2165.461395740509,
        "flops_time_in_seconds": 16.843998908996582,
        "flops": 34964942,
        "params_time_in_seconds": 16.564918041229248,
        "params": 20891
    },
    "{'graph': 'dis4', 'input_width': 12, 'num_input_modules': 1, 'initial_block_type': 'mbconv', 'initial_residual': 'module', 'input_temporal_scales': 1, 'initial_main_width': 10, 'num_main_levels': 2, 'num_main_level_modules': 2, 'block_type': 'basic', 'bottleneck_factor': 2, 'residual': 'null', 'main_temporal_scales': 3, 'temporal_kernel_size': 7, 'se': 'outer', 'se_ratio': 2, 'se_type': 'absolute', 'nonlinearity': 'relu', 'attention': 'frame', 'pool': 'spatial'}": {
        "synflow_time_in_seconds": 15.353774785995483,
        "synflow": 8.886509580456728e+174,
        "snip_time_in_seconds": 14.830501079559326,
        "snip": 4213.41015625,
        "grad_norm_time_in_seconds": 14.72437596321106,
        "grad_norm": 1809.30615234375,
        "fisher_time_in_seconds": 14.430447578430176,
        "fisher": 2495.41650390625,
        "grasp_time_in_seconds": 16.45432996749878,
        "grasp": 1572491.375,
        "val_accuracy": 0.9281045751633987,
        "num_parameters": 225695,
        "num_flops": 340435672,
        "best_loss": 0.5919243693351746,
        "best_auc": 0.9281045751633987,
        "training_validation_time_in_seconds": 21284.83744263649,
        "flops_time_in_seconds": 18.985453844070435,
        "flops": 334802712,
        "params_time_in_seconds": 17.765725135803223,
        "params": 225695
    },
    "{'graph': 'dis4+2', 'input_width': 12, 'num_input_modules': 3, 'initial_block_type': 'bottleneck', 'initial_residual': 'module', 'input_temporal_scales': 2, 'initial_main_width': 8, 'num_main_levels': 1, 'num_main_level_modules': 1, 'block_type': 'bottleneck', 'bottleneck_factor': 2, 'residual': 'module', 'main_temporal_scales': 1, 'temporal_kernel_size': 7, 'se': 'both', 'se_ratio': 4, 'se_type': 'relative', 'nonlinearity': 'relu', 'attention': 'null', 'pool': 'spatial'}": {
        "synflow_time_in_seconds": 23.20858359336853,
        "synflow": 2.950014199846095e+24,
        "snip_time_in_seconds": 21.996711015701294,
        "snip": 1701.2017822265625,
        "grad_norm_time_in_seconds": 22.00605034828186,
        "grad_norm": 646.8651123046875,
        "fisher_time_in_seconds": 21.69764232635498,
        "fisher": 381.119873046875,
        "grasp_time_in_seconds": 23.972201824188232,
        "grasp": -27581.025390625,
        "flops_time_in_seconds": 21.395992279052734,
        "flops": 448713370,
        "params_time_in_seconds": 21.0894136428833,
        "params": 107304,
        "val_accuracy": 0.9782135076252724,
        "num_parameters": 107304,
        "num_flops": 463207570,
        "best_loss": 0.49904513359069824,
        "best_auc": 0.9782135076252724,
        "training_validation_time_in_seconds": 12823.666647911072
    },
    "{'graph': 'dis4+2', 'input_width': 6, 'num_input_modules': 3, 'initial_block_type': 'bottleneck', 'initial_residual': 'null', 'input_temporal_scales': 'linear', 'initial_main_width': 12, 'num_main_levels': 2, 'num_main_level_modules': 2, 'block_type': 'mbconv', 'bottleneck_factor': 2, 'residual': 'module', 'main_temporal_scales': 1, 'temporal_kernel_size': 3, 'se': 'both', 'se_ratio': 4, 'se_type': 'relative', 'nonlinearity': 'swish', 'attention': 'null', 'pool': 'spatial'}": {
        "synflow_time_in_seconds": 21.424956798553467,
        "synflow": 9.730684783484124e+19,
        "snip_time_in_seconds": 15.340624809265137,
        "snip": 2627.55712890625,
        "grad_norm_time_in_seconds": 21.40528106689453,
        "grad_norm": 1819.97021484375,
        "fisher_time_in_seconds": 21.655537366867065,
        "fisher": 1645.5362548828125,
        "grasp_time_in_seconds": 23.79424476623535,
        "grasp": -233990.90625,
        "flops_time_in_seconds": 22.270115852355957,
        "flops": 116065938,
        "params_time_in_seconds": 21.436020374298096,
        "params": 85234,
        "val_accuracy": 0.9411764705882353,
        "num_parameters": 85234,
        "num_flops": 126776682,
        "best_loss": 0.547207236289978,
        "best_auc": 0.9411764705882353,
        "training_validation_time_in_seconds": 8002.338924407959
    },
    "{'graph': 'dis4', 'input_width': 10, 'num_input_modules': 3, 'initial_block_type': 'mbconv', 'initial_residual': 'dense', 'input_temporal_scales': 3, 'initial_main_width': 8, 'num_main_levels': 2, 'num_main_level_modules': 3, 'block_type': 'bottleneck', 'bottleneck_factor': 4, 'residual': 'dense', 'main_temporal_scales': 2, 'temporal_kernel_size': 9, 'se': 'outer', 'se_ratio': 2, 'se_type': 'absolute', 'nonlinearity': 'relu', 'attention': 'null', 'pool': 'global'}": {
        "synflow_time_in_seconds": 18.425161600112915,
        "synflow": 7.680484969895532e+51,
        "snip_time_in_seconds": 15.82325291633606,
        "snip": 1195.91748046875,
        "grad_norm_time_in_seconds": 16.075429677963257,
        "grad_norm": 462.7283630371094,
        "fisher_time_in_seconds": 16.101687908172607,
        "fisher": 223.80401611328125,
        "grasp_time_in_seconds": 21.611745357513428,
        "grasp": -77.867431640625,
        "flops_time_in_seconds": 16.088836431503296,
        "flops": 976745490,
        "params_time_in_seconds": 14.865110635757446,
        "params": 258948,
        "val_accuracy": 0.9586056644880174,
        "num_parameters": 258948,
        "num_flops": 1008513714,
        "best_loss": 0.5141773223876953,
        "best_auc": 0.9586056644880174,
        "training_validation_time_in_seconds": 22075.580880641937
    },
    "{'graph': 'dis4+2', 'input_width': 10, 'num_input_modules': 3, 'initial_block_type': 'bottleneck', 'initial_residual': 'dense', 'input_temporal_scales': 'linear', 'initial_main_width': 8, 'num_main_levels': 2, 'num_main_level_modules': 1, 'block_type': 'basic', 'bottleneck_factor': 4, 'residual': 'block', 'main_temporal_scales': 'linear', 'temporal_kernel_size': 9, 'se': 'inner', 'se_ratio': 4, 'se_type': 'relative', 'nonlinearity': 'relu', 'attention': 'channel', 'pool': 'global'}": {
        "synflow_time_in_seconds": 20.926278591156006,
        "synflow": 2.7141211783098145e+20,
        "snip_time_in_seconds": 21.981242895126343,
        "snip": 435.2839050292969,
        "grad_norm_time_in_seconds": 21.634034633636475,
        "grad_norm": 127.12532806396484,
        "fisher_time_in_seconds": 22.225417852401733,
        "fisher": 27.684553146362305,
        "grasp_time_in_seconds": 25.283047914505005,
        "grasp": -77.64901733398438,
        "flops_time_in_seconds": 21.53071641921997,
        "flops": 2817998282,
        "params_time_in_seconds": 21.15071129798889,
        "params": 580174,
        "val_accuracy": 0.9825708061002179,
        "num_parameters": 580174,
        "num_flops": 2838035190,
        "best_loss": 0.45291751623153687,
        "best_auc": 0.9825708061002179,
        "training_validation_time_in_seconds": 24993.338877916336
    },
    "{'graph': 'spatial', 'input_width': 6, 'num_input_modules': 3, 'initial_block_type': 'bottleneck', 'initial_residual': 'module', 'input_temporal_scales': 2, 'initial_main_width': 6, 'num_main_levels': 2, 'num_main_level_modules': 2, 'block_type': 'basic', 'bottleneck_factor': 2, 'residual': 'null', 'main_temporal_scales': 1, 'temporal_kernel_size': 3, 'se': 'both', 'se_ratio': 2, 'se_type': 'relative', 'nonlinearity': 'swish', 'attention': 'joint', 'pool': 'global'}": {
        "synflow_time_in_seconds": 15.277844190597534,
        "synflow": 277253571118035.78,
        "snip_time_in_seconds": 15.622767925262451,
        "snip": 104.87329864501953,
        "grad_norm_time_in_seconds": 15.223592519760132,
        "grad_norm": 62.41310501098633,
        "fisher_time_in_seconds": 14.806885242462158,
        "fisher": 1.907310962677002,
        "grasp_time_in_seconds": 16.563312768936157,
        "grasp": -868.0004272460938,
        "flops_time_in_seconds": 15.284905433654785,
        "flops": 147327624,
        "params_time_in_seconds": 15.129185914993286,
        "params": 90540,
        "val_accuracy": 0.6350762527233115,
        "num_parameters": 90540,
        "num_flops": 154169668,
        "best_loss": 0.7578365802764893,
        "best_auc": 0.6350762527233115,
        "training_validation_time_in_seconds": 1098.8993351459503
    },
    "{'graph': 'dis2', 'input_width': 10, 'num_input_modules': 3, 'initial_block_type': 'basic', 'initial_residual': 'dense', 'input_temporal_scales': 'linear', 'initial_main_width': 6, 'num_main_levels': 1, 'num_main_level_modules': 1, 'block_type': 'bottleneck', 'bottleneck_factor': 2, 'residual': 'block', 'main_temporal_scales': 1, 'temporal_kernel_size': 9, 'se': 'inner', 'se_ratio': 2, 'se_type': 'relative', 'nonlinearity': 'relu', 'attention': 'joint', 'pool': 'global'}": {
        "synflow_time_in_seconds": 15.023412227630615,
        "synflow": 3.8786665007969505e+18,
        "snip_time_in_seconds": 15.30938172340393,
        "snip": 40.27882766723633,
        "grad_norm_time_in_seconds": 14.99852728843689,
        "grad_norm": 18.71544075012207,
        "fisher_time_in_seconds": 14.637659788131714,
        "fisher": 0.9858440160751343,
        "grasp_time_in_seconds": 17.182488679885864,
        "grasp": -1.3290343284606934,
        "flops_time_in_seconds": 15.43473768234253,
        "flops": 368954442,
        "params_time_in_seconds": 14.28395390510559,
        "params": 89366,
        "val_accuracy": 0.9041394335511983,
        "num_parameters": 89366,
        "num_flops": 381561022,
        "best_loss": 0.5551386475563049,
        "best_auc": 0.9041394335511983,
        "training_validation_time_in_seconds": 9734.155253887177
    },
    "{'graph': 'spatial', 'input_width': 10, 'num_input_modules': 3, 'initial_block_type': 'mbconv', 'initial_residual': 'null', 'input_temporal_scales': 2, 'initial_main_width': 6, 'num_main_levels': 2, 'num_main_level_modules': 3, 'block_type': 'mbconv', 'bottleneck_factor': 4, 'residual': 'module', 'main_temporal_scales': 2, 'temporal_kernel_size': 5, 'se': 'null', 'se_ratio': 2, 'se_type': 'relative', 'nonlinearity': 'relu', 'attention': 'null', 'pool': 'spatial'}": {},
    "{'graph': 'spatial', 'input_width': 12, 'num_input_modules': 2, 'initial_block_type': 'bottleneck', 'initial_residual': 'null', 'input_temporal_scales': 1, 'initial_main_width': 6, 'num_main_levels': 2, 'num_main_level_modules': 1, 'block_type': 'mbconv', 'bottleneck_factor': 4, 'residual': 'block', 'main_temporal_scales': 'linear', 'temporal_kernel_size': 5, 'se': 'null', 'se_ratio': 4, 'se_type': 'relative', 'nonlinearity': 'relu', 'attention': 'joint', 'pool': 'global'}": {},
    "{'graph': 'dis4+2', 'input_width': 12, 'num_input_modules': 1, 'initial_block_type': 'mbconv', 'initial_residual': 'null', 'input_temporal_scales': 1, 'initial_main_width': 6, 'num_main_levels': 1, 'num_main_level_modules': 1, 'block_type': 'mbconv', 'bottleneck_factor': 4, 'residual': 'block', 'main_temporal_scales': 3, 'temporal_kernel_size': 7, 'se': 'both', 'se_ratio': 4, 'se_type': 'relative', 'nonlinearity': 'swish', 'attention': 'joint', 'pool': 'global'}": {},
    "{'graph': 'dis4+2', 'input_width': 8, 'num_input_modules': 3, 'initial_block_type': 'bottleneck', 'initial_residual': 'module', 'input_temporal_scales': 'linear', 'initial_main_width': 10, 'num_main_levels': 1, 'num_main_level_modules': 2, 'block_type': 'basic', 'bottleneck_factor': 4, 'residual': 'null', 'main_temporal_scales': 2, 'temporal_kernel_size': 5, 'se': 'inner', 'se_ratio': 4, 'se_type': 'relative', 'nonlinearity': 'relu', 'attention': 'channel', 'pool': 'global'}": {},
    "{'graph': 'spatial', 'input_width': 8, 'num_input_modules': 3, 'initial_block_type': 'basic', 'initial_residual': 'module', 'input_temporal_scales': 'linear', 'initial_main_width': 12, 'num_main_levels': 1, 'num_main_level_modules': 1, 'block_type': 'bottleneck', 'bottleneck_factor': 4, 'residual': 'dense', 'main_temporal_scales': 'linear', 'temporal_kernel_size': 7, 'se': 'inner', 'se_ratio': 4, 'se_type': 'relative', 'nonlinearity': 'swish', 'attention': 'channel', 'pool': 'spatial'}": {}
}